compat_patcher_core/__init__.py
compat_patcher_core/exceptions.py
compat_patcher_core/import_proxifier.py
compat_patcher_core/readme_generator.py
compat_patcher_core/registry.py
compat_patcher_core/runner.py
compat_patcher_core/scaffolding.py
compat_patcher_core/utilities.py
compat_patcher_core-2.3.dist-info/licenses/AUTHORS
compat_patcher_core-2.3.dist-info/licenses/LICENSE
compat_patcher_core-2.3.dist-info/METADATA
compat_patcher_core-2.3.dist-info/WHEEL
compat_patcher_core-2.3.dist-info/top_level.txt
compat_patcher_core-2.3.dist-info/RECORD
