Metadata-Version: 2.4
Name: compat-patcher-core
Version: 2.3
Summary: A patcher system to allow easy and lasting API compatibility
Author-email: Pascal Chambon <pythoniks@gmail.com>
License: MIT
Project-URL: Repository, https://github.com/pakal/compat-patcher-core
Project-URL: Documentation, https://compat-patcher-core.readthedocs.io/
Classifier: Development Status :: 5 - Production/Stable
Classifier: Intended Audience :: Developers
Classifier: Intended Audience :: Information Technology
Classifier: Intended Audience :: System Administrators
Classifier: Programming Language :: Python :: 3.7
Classifier: Programming Language :: Python :: 3.8
Classifier: Programming Language :: Python :: 3.9
Classifier: Programming Language :: Python :: 3.10
Classifier: Programming Language :: Python :: 3.11
Classifier: Programming Language :: Python :: 3.12
Classifier: Programming Language :: Python :: 3.13
Classifier: Topic :: System :: Filesystems
Classifier: Topic :: Software Development :: Libraries :: Python Modules
Classifier: Operating System :: Microsoft :: Windows
Classifier: Operating System :: Unix
Classifier: Operating System :: MacOS :: MacOS X
Requires-Python: >=3.7
License-File: LICENSE
License-File: AUTHORS
Dynamic: license-file
